readin_ucinet/__init__.py
readin_ucinet-1.4.1.dist-info/LICENSE
readin_ucinet-1.4.1.dist-info/METADATA
readin_ucinet-1.4.1.dist-info/WHEEL
readin_ucinet-1.4.1.dist-info/top_level.txt
readin_ucinet-1.4.1.dist-info/RECORD
