Metadata-Version: 2.1
Name: readin-ucinet
Version: 1.4.1
Summary: Read in UCINET file as pandas DF
Home-page: https://github.com/hezbranch/readin_ucinet
Author: Hezekiah Branch
Author-email: hezekiah.branch.tufts@gmail.com
License: UNKNOWN
Platform: UNKNOWN
Classifier: Programming Language :: Python :: 3
Classifier: License :: OSI Approved :: MIT License
Classifier: Operating System :: OS Independent
Requires-Python: >=3
